LICENSE.md
README.md
nicovideo/__init__.py
nicovideo/apirawdicts.py
nicovideo/errors.py
nicovideo/py.typed
nicovideo/user.py
nicovideo/video.py
nicovideo_py-4.1.2.dist-info/LICENSE.md
nicovideo_py-4.1.2.dist-info/METADATA
nicovideo_py-4.1.2.dist-info/WHEEL
nicovideo_py-4.1.2.dist-info/RECORD
